stacks/__about__.py
stacks/__init__.py
stacks/__main__.py
stacks/aws.py
stacks/cf.py
stacks/cli.py
stacks/config.py
stacks/helpers.py
stacks/main.py
stacks/states.py
tests/__init__.py
tests/test_cf.py
tests/test_config.py
cfstacks-0.4.7.dist-info/LICENSE
cfstacks-0.4.7.dist-info/METADATA
cfstacks-0.4.7.dist-info/WHEEL
cfstacks-0.4.7.dist-info/entry_points.txt
cfstacks-0.4.7.dist-info/top_level.txt
cfstacks-0.4.7.dist-info/RECORD
